README.md
setup.cfg
setup.py
mathviz_hopper/__init__.py
mathviz_hopper/src/Scatter.py
mathviz_hopper/src/__init__.py
mathviz_hopper/src/__init__.pyc
mathviz_hopper/src/bottle.py
mathviz_hopper/src/bottle.pyc
mathviz_hopper/src/cuts.txt
mathviz_hopper/src/data
mathviz_hopper/src/helpers.py
mathviz_hopper/src/helpers.pyc
mathviz_hopper/src/indices.py
mathviz_hopper/src/indices.pyc
mathviz_hopper/src/server.py
mathviz_hopper/src/server.pyc
mathviz_hopper/src/server_helpers.py
mathviz_hopper/src/server_helpers.pyc
mathviz_hopper/src/table.py
mathviz_hopper/src/table.pyc
mathviz_hopper/src/test.pyc
mathviz_hopper/src/data/index
mathviz_hopper/src/data/table
mathviz_hopper/src/data/table/asset-manifest.json
mathviz_hopper/src/data/table/favicon.ico
mathviz_hopper/src/data/table/fonts
mathviz_hopper/src/data/table/index.html
mathviz_hopper/src/data/table/katex.css
mathviz_hopper/src/data/table/manifest.json
mathviz_hopper/src/data/table/service-worker.js
mathviz_hopper/src/data/table/settings.json
mathviz_hopper/src/data/table/static
mathviz_hopper/src/data/table/fonts/KaTeX_AMS-Regular.eot
mathviz_hopper/src/data/table/fonts/KaTeX_AMS-Regular.ttf
mathviz_hopper/src/data/table/fonts/KaTeX_AMS-Regular.woff
mathviz_hopper/src/data/table/fonts/KaTeX_AMS-Regular.woff2
mathviz_hopper/src/data/table/fonts/KaTeX_Caligraphic-Bold.eot
mathviz_hopper/src/data/table/fonts/KaTeX_Caligraphic-Bold.ttf
mathviz_hopper/src/data/table/fonts/KaTeX_Caligraphic-Bold.woff
mathviz_hopper/src/data/table/fonts/KaTeX_Caligraphic-Bold.woff2
mathviz_hopper/src/data/table/fonts/KaTeX_Caligraphic-Regular.eot
mathviz_hopper/src/data/table/fonts/KaTeX_Caligraphic-Regular.ttf
mathviz_hopper/src/data/table/fonts/KaTeX_Caligraphic-Regular.woff
mathviz_hopper/src/data/table/fonts/KaTeX_Caligraphic-Regular.woff2
mathviz_hopper/src/data/table/fonts/KaTeX_Fraktur-Bold.eot
mathviz_hopper/src/data/table/fonts/KaTeX_Fraktur-Bold.ttf
mathviz_hopper/src/data/table/fonts/KaTeX_Fraktur-Bold.woff
mathviz_hopper_dev.egg-info/PKG-INFO
mathviz_hopper_dev.egg-info/SOURCES.txt
mathviz_hopper_dev.egg-info/dependency_links.txt
mathviz_hopper_dev.egg-info/top_level.txt